azureml/__init__.py
azureml/contrib/__init__.py
azureml/contrib/server/__init__.py
azureml/contrib/server/sdk.py
azureml/contrib/server/server.py
azureml_contrib_server-1.60.0.dist-info/licenses/LICENSE.txt
azureml_contrib_server-1.60.0.dist-info/METADATA
azureml_contrib_server-1.60.0.dist-info/WHEEL
azureml_contrib_server-1.60.0.dist-info/top_level.txt
azureml_contrib_server-1.60.0.dist-info/RECORD
